<?xml version="1.0"?>
<!--Phoronix Test Suite v6.8.0m1-->
<PhoronixTestSuite>
  <Generated>
    <Title>btrfs-ssd</Title>
    <LastModified>2017-04-06 00:15:31</LastModified>
    <TestClient>Phoronix Test Suite v6.8.0m1 (Tana)</TestClient>
    <Description>2 x Intel Xeon E5-2630 v3 testing with a HP 2129 v1.01 and NVIDIA Device 11b4 4096MB on Ubuntu 14.04 via the Phoronix Test Suite.</Description>
  </Generated>
  <System>
    <Identifier>btrfs-ssd</Identifier>
    <Hardware>Processor: 2 x Intel Xeon E5-2630 v3 @ 3.20GHz (32 Cores), Motherboard: HP 2129 v1.01, Chipset: Intel Haswell-E DMI2, Memory: 16 x 16384 MB 1866MHz Hynix, Disk: 2 x 960GB SanDisk SDSSDHII + 1200GB INTEL SSDPE2MW012T4, Graphics: NVIDIA Device 11b4 4096MB, Audio: Realtek ALC221, Network: Intel Connection</Hardware>
    <Software>OS: Ubuntu 14.04, Kernel: 4.11.0-rc3+ (x86_64) 20170327, Display Driver: nouveau 1.0.10, Compiler: GCC 4.8.4, File-System: btrfs, Screen Resolution: 1024x768</Software>
    <User>root</User>
    <TimeStamp>2017-04-05 23:00:06</TimeStamp>
    <TestClientVersion>6.8.0m1</TestClientVersion>
    <Notes>Python 2.7.6.</Notes>
    <JSON>{"compiler-configuration":"--build=x86_64-linux-gnu --disable-browser-plugin --disable-libmudflap --disable-werror --enable-checking=release --enable-clocale=gnu --enable-gnu-unique-object --enable-gtk-cairo --enable-java-awt=gtk --enable-java-home --enable-languages=c,c++,java,go,d,fortran,objc,obj-c++ --enable-libstdcxx-debug --enable-libstdcxx-time=yes --enable-multiarch --enable-nls --enable-objc-gc --enable-plugin --enable-shared --enable-threads=posix --host=x86_64-linux-gnu --target=x86_64-linux-gnu --with-abi=m64 --with-arch-32=i686 --with-arch-directory=amd64 --with-multilib-list=m32,m64,mx32 --with-tune=generic -v","disk-scheduler":"DEADLINE","disk-mount-options":"data=ordered,errors=remount-ro,relatime,rw","cpu-scaling-governor":"intel_pstate powersave"}</JSON>
  </System>
  <Result>
    <Identifier>pts/aio-stress-1.1.1</Identifier>
    <Title>AIO-Stress</Title>
    <AppVersion>0.21</AppVersion>
    <Arguments>-o 2</Arguments>
    <Description>Test: Random Write</Description>
    <Scale>MB/s</Scale>
    <Proportion>HIB</Proportion>
    <DisplayFormat>BAR_GRAPH</DisplayFormat>
    <Data>
      <Entry>
        <Identifier>btrfs-ssd</Identifier>
        <Value>2105.95</Value>
        <RawString>2103.11:2102.75:2111.99</RawString>
        <JSON>{"compiler-options":{"compiler-type":"CC","compiler":"gcc","compiler-options":"-pthread -laio"}}</JSON>
      </Entry>
    </Data>
  </Result>
  <Result>
    <Identifier>pts/fio-1.8.2</Identifier>
    <Title>Flexible IO Tester</Title>
    <AppVersion>2.1.13</AppVersion>
    <Arguments>randread sync 1 0 4k  IOPS</Arguments>
    <Description>Type: Random Read - IO Engine: Sync - Buffered: Yes - Direct: No - Block Size: 4KB - Disk Target: Default Test Directory - Result: IOPS</Description>
    <Scale>IOPS</Scale>
    <Proportion>HIB</Proportion>
    <DisplayFormat>BAR_GRAPH</DisplayFormat>
    <Data>
      <Entry>
        <Identifier>btrfs-ssd</Identifier>
        <Value>7037</Value>
        <RawString>6949:6983:7179</RawString>
        <JSON>{"compiler-options":{"compiler-type":"CC","compiler":"gcc","compiler-options":"-rdynamic -std=gnu99 -O3 -ffast-math -include -ll -lnuma -lrt -laio -lz -lm -lpthread -ldl"}}</JSON>
      </Entry>
    </Data>
  </Result>
  <Result>
    <Identifier>pts/fio-1.8.2</Identifier>
    <Title>Flexible IO Tester</Title>
    <AppVersion>2.1.13</AppVersion>
    <Arguments>randwrite sync 1 0 4k  IOPS</Arguments>
    <Description>Type: Random Write - IO Engine: Sync - Buffered: Yes - Direct: No - Block Size: 4KB - Disk Target: Default Test Directory - Result: IOPS</Description>
    <Scale>IOPS</Scale>
    <Proportion>HIB</Proportion>
    <DisplayFormat>BAR_GRAPH</DisplayFormat>
    <Data>
      <Entry>
        <Identifier>btrfs-ssd</Identifier>
        <Value>26940</Value>
        <RawString>54832:19040:15477:23700:20992:27601</RawString>
        <JSON>{"compiler-options":{"compiler-type":"CC","compiler":"gcc","compiler-options":"-rdynamic -std=gnu99 -O3 -ffast-math -include -ll -lnuma -lrt -laio -lz -lm -lpthread -ldl"}}</JSON>
      </Entry>
    </Data>
  </Result>
  <Result>
    <Identifier>pts/fio-1.8.2</Identifier>
    <Title>Flexible IO Tester</Title>
    <AppVersion>2.1.13</AppVersion>
    <Arguments>read sync 1 0 1m  MBS</Arguments>
    <Description>Type: Sequential Read - IO Engine: Sync - Buffered: Yes - Direct: No - Block Size: 1MB - Disk Target: Default Test Directory - Result: MB/s</Description>
    <Scale>MB/s</Scale>
    <Proportion>HIB</Proportion>
    <DisplayFormat>BAR_GRAPH</DisplayFormat>
    <Data>
      <Entry>
        <Identifier>btrfs-ssd</Identifier>
        <Value>449.19</Value>
        <RawString>413.163:456.909:456.368:456.044:458.113:454.542</RawString>
        <JSON>{"compiler-options":{"compiler-type":"CC","compiler":"gcc","compiler-options":"-rdynamic -std=gnu99 -O3 -ffast-math -include -ll -lnuma -lrt -laio -lz -lm -lpthread -ldl"}}</JSON>
      </Entry>
    </Data>
  </Result>
  <Result>
    <Identifier>pts/fio-1.8.2</Identifier>
    <Title>Flexible IO Tester</Title>
    <AppVersion>2.1.13</AppVersion>
    <Arguments>write sync 1 0 1m  MBS</Arguments>
    <Description>Type: Sequential Write - IO Engine: Sync - Buffered: Yes - Direct: No - Block Size: 1MB - Disk Target: Default Test Directory - Result: MB/s</Description>
    <Scale>MB/s</Scale>
    <Proportion>HIB</Proportion>
    <DisplayFormat>BAR_GRAPH</DisplayFormat>
    <Data>
      <Entry>
        <Identifier>btrfs-ssd</Identifier>
        <Value>469.39</Value>
        <RawString>463.736:475.01:469.418</RawString>
        <JSON>{"compiler-options":{"compiler-type":"CC","compiler":"gcc","compiler-options":"-rdynamic -std=gnu99 -O3 -ffast-math -include -ll -lnuma -lrt -laio -lz -lm -lpthread -ldl"}}</JSON>
      </Entry>
    </Data>
  </Result>
  <Result>
    <Identifier>pts/fs-mark-1.0.1</Identifier>
    <Title>FS-Mark</Title>
    <AppVersion>3.3</AppVersion>
    <Arguments>-s 1048576 -n 1000</Arguments>
    <Description>Test: 1000 Files, 1MB Size</Description>
    <Scale>Files/s</Scale>
    <Proportion>HIB</Proportion>
    <DisplayFormat>BAR_GRAPH</DisplayFormat>
    <Data>
      <Entry>
        <Identifier>btrfs-ssd</Identifier>
        <Value>162.00</Value>
        <RawString>161.4:163.3:161.3</RawString>
        <JSON>{"compiler-options":{"compiler-type":"CC","compiler":"gcc","compiler-options":"-static"}}</JSON>
      </Entry>
    </Data>
  </Result>
  <Result>
    <Identifier>pts/fs-mark-1.0.1</Identifier>
    <Title>FS-Mark</Title>
    <AppVersion>3.3</AppVersion>
    <Arguments>-s 1048576 -n 5000 -t 4</Arguments>
    <Description>Test: 5000 Files, 1MB Size, 4 Threads</Description>
    <Scale>Files/s</Scale>
    <Proportion>HIB</Proportion>
    <DisplayFormat>BAR_GRAPH</DisplayFormat>
    <Data>
      <Entry>
        <Identifier>btrfs-ssd</Identifier>
        <Value>212.13</Value>
        <RawString>215.8:210.4:210.2</RawString>
        <JSON>{"compiler-options":{"compiler-type":"CC","compiler":"gcc","compiler-options":"-static"}}</JSON>
      </Entry>
    </Data>
  </Result>
  <Result>
    <Identifier>pts/fs-mark-1.0.1</Identifier>
    <Title>FS-Mark</Title>
    <AppVersion>3.3</AppVersion>
    <Arguments>-s 1048576 -n 4000 -D 32</Arguments>
    <Description>Test: 4000 Files, 32 Sub Dirs, 1MB Size</Description>
    <Scale>Files/s</Scale>
    <Proportion>HIB</Proportion>
    <DisplayFormat>BAR_GRAPH</DisplayFormat>
    <Data>
      <Entry>
        <Identifier>btrfs-ssd</Identifier>
        <Value>145.57</Value>
        <RawString>151.1:142.7:142.9</RawString>
        <JSON>{"compiler-options":{"compiler-type":"CC","compiler":"gcc","compiler-options":"-static"}}</JSON>
      </Entry>
    </Data>
  </Result>
  <Result>
    <Identifier>pts/fs-mark-1.0.1</Identifier>
    <Title>FS-Mark</Title>
    <AppVersion>3.3</AppVersion>
    <Arguments>-s 1048576 -n 1000 -S 0</Arguments>
    <Description>Test: 1000 Files, 1MB Size, No Sync/FSync</Description>
    <Scale>Files/s</Scale>
    <Proportion>HIB</Proportion>
    <DisplayFormat>BAR_GRAPH</DisplayFormat>
    <Data>
      <Entry>
        <Identifier>btrfs-ssd</Identifier>
        <Value>1834.23</Value>
        <RawString>1824.2:1825.1:1853.4</RawString>
        <JSON>{"compiler-options":{"compiler-type":"CC","compiler":"gcc","compiler-options":"-static"}}</JSON>
      </Entry>
    </Data>
  </Result>
  <Result>
    <Identifier>pts/dbench-1.0.0</Identifier>
    <Title>Dbench</Title>
    <AppVersion>4.0</AppVersion>
    <Arguments>6</Arguments>
    <Description>Client Count: 6</Description>
    <Scale>MB/s</Scale>
    <Proportion>HIB</Proportion>
    <DisplayFormat>BAR_GRAPH</DisplayFormat>
    <Data>
      <Entry>
        <Identifier>btrfs-ssd</Identifier>
        <Value>483.82</Value>
        <RawString>484.782:487.522:479.154</RawString>
        <JSON>{"compiler-options":{"compiler-type":"CC","compiler":"gcc","compiler-options":"-lpopt -O2"}}</JSON>
      </Entry>
    </Data>
  </Result>
  <Result>
    <Identifier>pts/iozone-1.8.0</Identifier>
    <Title>IOzone</Title>
    <AppVersion>3.405</AppVersion>
    <Arguments>-r 1m -s 2048M -i0 -i1</Arguments>
    <Description>Record Size: 1MB - File Size: 2GB - Disk Test: Read Performance</Description>
    <Scale>MB/s</Scale>
    <Proportion>HIB</Proportion>
    <DisplayFormat>BAR_GRAPH</DisplayFormat>
    <Data>
      <Entry>
        <Identifier>btrfs-ssd</Identifier>
        <Value>5007.75</Value>
        <RawString>4918.37109375:5048.6767578125:5056.1923828125</RawString>
        <JSON>{"compiler-options":{"compiler-type":"CC","compiler":"gcc","compiler-options":"-O3"}}</JSON>
      </Entry>
    </Data>
  </Result>
  <Result>
    <Identifier>pts/iozone-1.8.0</Identifier>
    <Title>IOzone</Title>
    <AppVersion>3.405</AppVersion>
    <Arguments>-r 1m -s 2048M -i0</Arguments>
    <Description>Record Size: 1MB - File Size: 2GB - Disk Test: Write Performance</Description>
    <Scale>MB/s</Scale>
    <Proportion>HIB</Proportion>
    <DisplayFormat>BAR_GRAPH</DisplayFormat>
    <Data>
      <Entry>
        <Identifier>btrfs-ssd</Identifier>
        <Value>393.74</Value>
        <RawString>393.958984375:393.2939453125:393.9716796875</RawString>
        <JSON>{"compiler-options":{"compiler-type":"CC","compiler":"gcc","compiler-options":"-O3"}}</JSON>
      </Entry>
    </Data>
  </Result>
  <Result>
    <Identifier>pts/tiobench-1.2.0</Identifier>
    <Title>Threaded I/O Tester</Title>
    <AppVersion>0.3.3</AppVersion>
    <Arguments>-k2 -k1 -f 64 -t 4</Arguments>
    <Description>Test: Random Read - Size Per Thread: 64MB - Thread Count: 4</Description>
    <Scale>MB/s</Scale>
    <Proportion>HIB</Proportion>
    <DisplayFormat>BAR_GRAPH</DisplayFormat>
    <Data>
      <Entry>
        <Identifier>btrfs-ssd</Identifier>
        <Value>7355.96</Value>
        <RawString>7270.824:7349.483:7447.569</RawString>
      </Entry>
    </Data>
  </Result>
  <Result>
    <Identifier>pts/tiobench-1.2.0</Identifier>
    <Title>Threaded I/O Tester</Title>
    <AppVersion>0.3.3</AppVersion>
    <Arguments>-k3 -k2 -f 64 -t 4</Arguments>
    <Description>Test: Random Write - Size Per Thread: 64MB - Thread Count: 4</Description>
    <Scale>MB/s</Scale>
    <Proportion>HIB</Proportion>
    <DisplayFormat>BAR_GRAPH</DisplayFormat>
    <Data>
      <Entry>
        <Identifier>btrfs-ssd</Identifier>
        <Value>5.28</Value>
        <RawString>4.057:6.351:6.203:2.487:6.282:6.296</RawString>
      </Entry>
    </Data>
  </Result>
  <Result>
    <Identifier>pts/compilebench-1.0.1</Identifier>
    <Title>Compile Bench</Title>
    <AppVersion>0.6</AppVersion>
    <Arguments>COMPILE</Arguments>
    <Description>Test: Compile</Description>
    <Scale>MB/s</Scale>
    <Proportion>HIB</Proportion>
    <DisplayFormat>BAR_GRAPH</DisplayFormat>
    <Data>
      <Entry>
        <Identifier>btrfs-ssd</Identifier>
        <Value>504.55</Value>
        <RawString>537.46:470.09:511.26:493.21:500.84:514.46</RawString>
      </Entry>
    </Data>
  </Result>
  <Result>
    <Identifier>pts/unpack-linux-1.0.0</Identifier>
    <Title>Unpacking The Linux Kernel</Title>
    <AppVersion></AppVersion>
    <Arguments></Arguments>
    <Description>linux-2.6.32.tar.bz2</Description>
    <Scale>Seconds</Scale>
    <Proportion>LIB</Proportion>
    <DisplayFormat>BAR_GRAPH</DisplayFormat>
    <Data>
      <Entry>
        <Identifier>btrfs-ssd</Identifier>
        <Value>11.53</Value>
        <RawString>11.546403884888:11.700858831406:11.60639500618:11.268925905228</RawString>
      </Entry>
    </Data>
  </Result>
  <Result>
    <Identifier>pts/postmark-1.1.0</Identifier>
    <Title>PostMark</Title>
    <AppVersion>1.51</AppVersion>
    <Arguments></Arguments>
    <Description>Disk Transaction Performance</Description>
    <Scale>TPS</Scale>
    <Proportion>HIB</Proportion>
    <DisplayFormat>BAR_GRAPH</DisplayFormat>
    <Data>
      <Entry>
        <Identifier>btrfs-ssd</Identifier>
        <Value>4630</Value>
        <RawString>4629:4545:4716</RawString>
        <JSON>{"compiler-options":{"compiler-type":"CC","compiler":"gcc","compiler-options":"-O3"}}</JSON>
      </Entry>
    </Data>
  </Result>
</PhoronixTestSuite>
